Metadata-Version: 2.1
Name: ont-bonito-cuda111
Version: 0.5.3
Summary: UNKNOWN
Home-page: https://github.com/nanoporetech/bonito
Author: Oxford Nanopore Technologies, Ltd
Author-email: support@nanoporetech.com
License: UNKNOWN
Platform: UNKNOWN
